sphinx_inline_tabs/__init__.py
sphinx_inline_tabs/_impl.py
sphinx_inline_tabs/static/tabs.css
sphinx_inline_tabs/static/tabs.js
sphinx_inline_tabs-2022.1.2b11.dist-info/LICENSE
sphinx_inline_tabs-2022.1.2b11.dist-info/WHEEL
sphinx_inline_tabs-2022.1.2b11.dist-info/METADATA
sphinx_inline_tabs-2022.1.2b11.dist-info/RECORD
