Metadata-Version: 2.1
Name: sphinx_inline_tabs
Version: 2022.1.2b11
Summary: Add inline tabbed content to your Sphinx documentation.
Home-page: https://github.com/pradyunsg/sphinx-inline-tabs
Author: Pradyun Gedam
Author-email: mail@pradyunsg.me
Requires-Python: >=3.8
Requires-Dist: sphinx >= 3
Requires-Dist: myst-parser ; extra == "doc"
Requires-Dist: furo ; extra == "doc"
Requires-Dist: pytest ; extra == "test"
Requires-Dist: pytest-cov ; extra == "test"
Requires-Dist: pytest-xdist ; extra == "test"
Provides-Extra: doc
Provides-Extra: test
